StringProgressBar/__init__.py
StringProgressBar-1.1.0.dist-info/LICENSE
StringProgressBar-1.1.0.dist-info/METADATA
StringProgressBar-1.1.0.dist-info/WHEEL
StringProgressBar-1.1.0.dist-info/top_level.txt
StringProgressBar-1.1.0.dist-info/RECORD
