Metadata-Version: 2.1
Name: StringProgressBar
Version: 1.1.0
Summary: Simple string progress bar made for discord bots. Its usable everywhere.
Home-page: https://github.com/MrJacob12/StringProgressBar
Author: MrJacob, Sparker-99
Author-email: jacob@fern.fun
License: MIT
Keywords: String Progress Bar
Platform: UNKNOWN
Classifier: Development Status :: 5 - Production/Stable
Classifier: Intended Audience :: Education
Classifier: Operating System :: Microsoft :: Windows :: Windows 10
Classifier: License :: OSI Approved :: MIT License
Classifier: Programming Language :: Python :: 3
